senasopt/__init__.py
senasopt/_version.py
senasopt/asset/__init__.py
senasopt/asset/battery.py
senasopt/asset/building.py
senasopt/asset/optimise.py
senasopt/asset/solar.py
senasopt/asset/wind.py
senasopt-0.4.dist-info/LICENSE
senasopt-0.4.dist-info/METADATA
senasopt-0.4.dist-info/WHEEL
senasopt-0.4.dist-info/top_level.txt
senasopt-0.4.dist-info/RECORD
