Metadata-Version: 2.1
Name: senasopt
Version: 0.4
Summary: Simple Energy Asset Optimisation (aka. senasopt) - A small example package trying out optimisation of energy-related assets
Home-page: https://gitlab.com/Pierre_VF/senasopt
Author: PVF
Author-email: pvf@dtime.ai
License: UNKNOWN
Platform: UNKNOWN
Classifier: Programming Language :: Python :: 3
Classifier: License :: OSI Approved :: MIT License
Classifier: Operating System :: OS Independent
Requires-Python: >=3.6
License-File: LICENSE
Requires-Dist: casadi
Requires-Dist: numpy
Requires-Dist: pandas
Requires-Dist: setuptools
Requires-Dist: xlrd
Provides-Extra: all
Requires-Dist: plotly ; extra == 'all'
Requires-Dist: dash ; extra == 'all'
Requires-Dist: black ; extra == 'all'
Requires-Dist: pytest ; extra == 'all'
Requires-Dist: versioneer ; extra == 'all'
Requires-Dist: coverage ; extra == 'all'
Requires-Dist: build ; extra == 'all'
Requires-Dist: pre-commit ; extra == 'all'
Provides-Extra: dev
Requires-Dist: black ; extra == 'dev'
Requires-Dist: pytest ; extra == 'dev'
Requires-Dist: versioneer ; extra == 'dev'
Requires-Dist: coverage ; extra == 'dev'
Requires-Dist: build ; extra == 'dev'
Requires-Dist: pre-commit ; extra == 'dev'
